<?xml version="1.0" encoding="UTF-8"?>
<!DOCTYPE suite SYSTEM "https://testng.org/testng-1.0.dtd">
<suite name="Suite" thread-count="5" parallel="tests">
  <test  name="Test runner 1">
    <classes>
      <class name="testScript.TC_3"/>
      <class name="testScript.ConvertLeadToOpportunityTest"/>
    </classes>
  </test>
  <test name="Test runner 2">
  <classes>
      <class name="testScript.TC_3"/>
      <class name="testScript.ConvertLeadToOpportunityTest"/>
    </classes>
  </test>
  
   <!-- Test -->
</suite> <!-- Suite -->
